belo-0.2.2.dist-info/METADATA
belo-0.2.2.dist-info/WHEEL
belo-0.2.2.dist-info/licenses/LICENSE
belo/__init__.py
belo/belo.cpython-312-x86_64-linux-gnu.so
belo-0.2.2.dist-info/RECORD
