Metadata-Version: 2.4
Name: belo
Version: 0.2.2
License-File: LICENSE
Summary: A fast bayesian elo rating system, written in Rust.
Keywords: rust,elo,glicko
Author: 송재헌 <jhun.song@samsung.com>
Author-email: 송재헌 <jhun.song@samsung.com>
License: Apache-2.0
Project-URL: Source Code, https://github.sec.samsung.net/SR-SE/belo
